odoo10_addon_onchange_helper-10.0.3.1.2-nspkg.pth
odoo/addons/onchange_helper/README.rst
odoo/addons/onchange_helper/__init__.py
odoo/addons/onchange_helper/__manifest__.py
odoo/addons/onchange_helper/i18n/de.po
odoo/addons/onchange_helper/i18n/es.po
odoo/addons/onchange_helper/i18n/hr.po
odoo/addons/onchange_helper/i18n/it.po
odoo/addons/onchange_helper/i18n/onchange_helper.pot
odoo/addons/onchange_helper/i18n/sl.po
odoo/addons/onchange_helper/models/__init__.py
odoo/addons/onchange_helper/models/models.py
odoo/addons/onchange_helper/static/description/icon.png
odoo/addons/onchange_helper/tests/__init__.py
odoo/addons/onchange_helper/tests/test_onchange.py
odoo10_addon_onchange_helper-10.0.3.1.2.dist-info/METADATA
odoo10_addon_onchange_helper-10.0.3.1.2.dist-info/WHEEL
odoo10_addon_onchange_helper-10.0.3.1.2.dist-info/namespace_packages.txt
odoo10_addon_onchange_helper-10.0.3.1.2.dist-info/top_level.txt
odoo10_addon_onchange_helper-10.0.3.1.2.dist-info/RECORD
