Metadata-Version: 2.1
Name: odoo10-addon-onchange-helper
Version: 10.0.3.1.2
Summary: Technical module that ease execution of onchange in Python code
Home-page: https://github.com/OCA/server-tools
Author: Akretion,Camptocamp, ACSONE SA/NV, Odoo Community Association (OCA)
Author-email: support@odoo-community.org
License: AGPL-3
Platform: UNKNOWN
Classifier: Programming Language :: Python
Classifier: Framework :: Odoo
Classifier: License :: OSI Approved :: GNU Affero General Public License v3
Requires-Python: ~=2.7
Requires-Dist: odoo (<10.1dev,>=10.0)
